cfstack/__init__.py
cfstack/execute.py
cfstack/changeset/__init__.py
cfstack/changeset/check_changeset_status.py
cfstack/changeset/create_changeset.py
cfstack/changeset/delete_changeset.py
cfstack/changeset/execute_changeset.py
cfstack/changeset/generate_changesetname.py
cfstack/s3utility/__init__.py
cfstack/s3utility/create_client.py
cfstack/s3utility/delete_file_s3.py
cfstack/s3utility/read_file_s3.py
cfstack/s3utility/upload_file_s3.py
cfstack/stack/__init__.py
cfstack/stack/check_stack_delete_status.py
cfstack/stack/check_stack_exists.py
cfstack/stack/check_stack_update_status.py
cfstack/stack/delete_stack.py
cfstack/utility/__init__.py
cfstack/utility/calculate_shamap.py
cfstack/utility/compare_shamap.py
cfstack/utility/create_client.py
cfstack/utility/execute_delete.py
cfstack/utility/execute_deploy.py
cfstack/utility/first_time_upload.py
cfstack/utility/parameter_preprocessing.py
cfstack/utility/upload_template_s3.py
cfstack-1.2.1.dist-info/LICENSE
cfstack-1.2.1.dist-info/METADATA
cfstack-1.2.1.dist-info/WHEEL
cfstack-1.2.1.dist-info/top_level.txt
cfstack-1.2.1.dist-info/RECORD
