Metadata-Version: 2.1
Name: cfstack
Version: 1.2.1
Summary: A utility to manage CloudFormation stacks
Home-page: https://github.com/Yashprime1
Author: Yashdeep Suresh Shetty
Author-email: shettyyashdeep@gmail.com
Requires-Python: >=3
License-File: LICENSE
Requires-Dist: boto3
